[
  {
    "supplier": "mikar",
    "name": "lennon",
    "description": "Chaise Unit",
    "size": "3",
    "whitePrice": {
      "normal": 278.1,
      "leather": 292.01,
      "stripe": 278.1
    },
    "consumption": {
      "normal": 11.5,
      "railroad": 11.5,
      "hpNormal": 11.5,
      "hpRailroad": 11.5,
      "hpNormalStripe": 11.5,
      "hpRailroadStripe": 11.5,
      "leather": 14.5
    }
  },
  {
    "supplier": "mikar",
    "name": "lennon",
    "description": "Storage Chaise Sofabed",
    "size": "3",
    "whitePrice": {
      "normal": 464.98,
      "leather": 488.23,
      "stripe": 464.98
    },
    "consumption": {
      "normal": 11,
      "railroad": 11,
      "hpNormal": 11,
      "hpRailroad": 11,
      "hpNormalStripe": 11,
      "hpRailroadStripe": 11,
      "leather": 16.9
    }
  },
  {
    "supplier": "mikar",
    "name": "lennon",
    "description": "Large Sofa",
    "size": "3",
    "whitePrice": {
      "normal": 214.69,
      "leather": 225.43,
      "stripe": 214.69
    },
    "consumption": {
      "normal": 8.5,
      "railroad": 8.5,
      "hpNormal": 8.5,
      "hpRailroad": 8.5,
      "hpNormalStripe": 8.5,
      "hpRailroadStripe": 8.5,
      "leather": 10.18
    }
  },
  {
    "supplier": "mikar",
    "name": "lennon",
    "description": "Medium Sofa",
    "size": "2.5",
    "whitePrice": {
      "normal": 165.75,
      "leather": 174.03,
      "stripe": 165.75
    },
    "consumption": {
      "normal": 7.1,
      "railroad": 7.1,
      "hpNormal": 7.1,
      "hpRailroad": 7.1,
      "hpNormalStripe": 7.1,
      "hpRailroadStripe": 7.1,
      "leather": 9.43
    }
  },
  {
    "supplier": "mikar",
    "name": "lennon",
    "description": "Small Sofa",
    "size": "2",
    "whitePrice": {
      "normal": 147.95,
      "leather": 155.35,
      "stripe": 147.95
    },
    "consumption": {
      "normal": 6.2,
      "railroad": 6.2,
      "hpNormal": 6.2,
      "hpRailroad": 6.2,
      "hpNormalStripe": 6.2,
      "hpRailroadStripe": 6.2,
      "leather": 8.7
    }
  },
  {
    "supplier": "mikar",
    "name": "lennon",
    "description": "Snuggler",
    "size": "1.5",
    "whitePrice": {
      "normal": 131.26,
      "leather": 137.83,
      "stripe": 131.26
    },
    "consumption": {
      "normal": 4.6,
      "railroad": 4.6,
      "hpNormal": 4.6,
      "hpRailroad": 4.6,
      "hpNormalStripe": 4.6,
      "hpRailroadStripe": 4.6,
      "leather": 6.19
    }
  },
  {
    "supplier": "mikar",
    "name": "lennon",
    "description": "Chair",
    "size": "1",
    "whitePrice": {
      "normal": 102.34,
      "leather": 107.46,
      "stripe": 102.34
    },
    "consumption": {
      "normal": 4.2,
      "railroad": 4.2,
      "hpNormal": 4.2,
      "hpRailroad": 4.2,
      "hpNormalStripe": 4.2,
      "hpRailroadStripe": 4.2,
      "leather": 5.21
    }
  },
  {
    "supplier": "mikar",
    "name": "lennon",
    "description": "Stool",
    "size": "0.5",
    "whitePrice": {
      "normal": 64.52,
      "leather": 67.75,
      "stripe": 64.52
    },
    "consumption": {
      "normal": 1.5,
      "railroad": 1.5,
      "hpNormal": 1.5,
      "hpRailroad": 1.5,
      "hpNormalStripe": 1.5,
      "hpRailroadStripe": 1.5,
      "leather": 2.5
    }
  },
  {
    "supplier": "mikar",
    "name": "lennon",
    "description": "Scatters",
    "size": "0.25",
    "whitePrice": {
      "normal": 13.35,
      "leather": 14.02,
      "stripe": 13.35
    },
    "consumption": {
      "normal": 0.4,
      "railroad": 0.4,
      "hpNormal": 0.4,
      "hpRailroad": 0.4,
      "hpNormalStripe": 0.4,
      "hpRailroadStripe": 0.4,
      "leather": 1.01
    }
  },
  {
    "supplier": "mikar",
    "name": "lennon",
    "description": "Small Sofabed",
    "size": "2",
    "whitePrice": {
      "normal": 295.9,
      "leather": 310.69,
      "stripe": 295.9
    },
    "consumption": {
      "normal": 7.5,
      "railroad": 7.5,
      "hpNormal": 7.5,
      "hpRailroad": 7.5,
      "hpNormalStripe": 7.5,
      "hpRailroadStripe": 7.5,
      "leather": 8.9
    }
  },
  {
    "supplier": "mikar",
    "name": "lennon",
    "description": "Medium Sofabed",
    "size": "2.5",
    "whitePrice": {
      "normal": 304.8,
      "leather": 320.04,
      "stripe": 304.8
    },
    "consumption": {
      "normal": 8.2,
      "railroad": 8.2,
      "hpNormal": 8.2,
      "hpRailroad": 8.2,
      "hpNormalStripe": 8.2,
      "hpRailroadStripe": 8.2,
      "leather": 9.5
    }
  }
]
